pydiabas/__init__.py
pydiabas/exceptions.py
pydiabas/pydiabas.py
pydiabas/result.py
pydiabas/ecu/__init__.py
pydiabas/ecu/base.py
pydiabas/ecu/msd80.py
pydiabas/ediabas/__init__.py
pydiabas/ediabas/api32.py
pydiabas/ediabas/ediabas.py
pydiabas/ediabas/exceptions.py
pydiabas/ediabas/statics.py
pydiabas/ediabas/utils.py
pydiabas/simulation/__init__.py
pydiabas/simulation/capturing.py
pydiabas/simulation/simulated_pydiabas.py
test/__init__.py
test/conftest.py
test/test_ecu/__init__.py
test/test_ecu/test_base.py
test/test_ecu/test_msd80.py
test/test_ediabas/__init__.py
test/test_ediabas/test_ediabas.py
test/test_ediabas/test_utils.py
test/test_pydiabas/__init__.py
test/test_pydiabas/test_pydiabas.py
test/test_pydiabas/test_result.py
test/test_simulation/__init__.py
test/test_simulation/test_capturing.py
test/test_simulation/test_simulation.py
PyDIABAS-1.2.0.dist-info/LICENSE
PyDIABAS-1.2.0.dist-info/METADATA
PyDIABAS-1.2.0.dist-info/WHEEL
PyDIABAS-1.2.0.dist-info/top_level.txt
PyDIABAS-1.2.0.dist-info/RECORD
