Metadata-Version: 2.2
Name: PyDIABAS
Version: 1.2.0
Summary: Python access to EDIABAS API
Author-email: Aljoscha Greim <aljoscha@bembelbytes.com>
Project-URL: Homepage, https://github.com/BembelBytes/pydiabas
Classifier: Programming Language :: Python :: 3
Classifier: License :: OSI Approved :: MIT License
Requires-Python: >=3.10
License-File: LICENSE
